cinnaroll/__init__.py
cinnaroll_internal/__init__.py
cinnaroll_internal/constants.py
cinnaroll_internal/environment_check.py
cinnaroll_internal/environment_info.py
cinnaroll_internal/io_formats.py
cinnaroll_internal/jupyter_notebook.py
cinnaroll_internal/model.py
cinnaroll_internal/model_upload.py
cinnaroll_internal/post_training_validation.py
cinnaroll_internal/pre_training_validation.py
cinnaroll_internal/rollout.py
cinnaroll_internal/rollout_config.py
cinnaroll_internal/utils.py
cinnaroll_internal/working_environment.py
cinnaroll_internal/infer_func_deps_finder/__init__.py
cinnaroll_internal/infer_func_deps_finder/ast_utils.py
cinnaroll_internal/infer_func_deps_finder/deps_finder.py
cinnaroll_internal/infer_func_deps_finder/global_variables.py
cinnaroll_internal/infer_func_deps_finder/imports.py
cinnaroll_internal/infer_func_deps_finder/infer_func_file.py
cinnaroll_internal/infer_func_deps_finder/local_dependencies.py
cinnaroll_internal/infer_func_deps_finder/modules.py
cinnaroll_internal/infer_func_deps_finder/notebook_local_dependencies.py
cinnaroll_internal/infer_func_deps_finder/output_verification.py
cinnaroll_internal/infer_func_deps_finder/packages.py
cinnaroll_internal/infer_func_deps_finder/shadowed_names.py
cinnaroll_internal/infer_func_deps_finder/types.py
cli/__init__.py
cli/login.py
cinnaroll-0.6.3.dist-info/LICENSE
cinnaroll-0.6.3.dist-info/METADATA
cinnaroll-0.6.3.dist-info/WHEEL
cinnaroll-0.6.3.dist-info/entry_points.txt
cinnaroll-0.6.3.dist-info/top_level.txt
cinnaroll-0.6.3.dist-info/RECORD
