Metadata-Version: 2.1
Name: cinnaroll
Version: 0.6.3
Summary: Configuring, Packaging and Sending Machine Learning Models to Deployment at cinnaroll.ai
Home-page: https://github.com/carthago-cloud/cinnaroll-python-lib
Author: VirtusLab
Author-email: service@cinnaroll.ai
License: Apache License 2.0
Keywords: machine-learning,ml,deployment
Platform: UNKNOWN
Classifier: Programming Language :: Python
Classifier: Programming Language :: Python :: 3
Classifier: Development Status :: 1 - Planning
Classifier: Environment :: Console
Classifier: Intended Audience :: Developers
Classifier: Intended Audience :: Information Technology
Classifier: License :: OSI Approved :: Apache Software License
Classifier: Operating System :: OS Independent
Requires-Python: >=3.7, <4
License-File: LICENSE
Requires-Dist: Pillow (>=9.2.0)
Requires-Dist: asttokens (>=2.1.0)
Requires-Dist: importlib-metadata (>=6.0.0)
Requires-Dist: outdated (>=0.2.2)
Requires-Dist: requests (>=2.28.1)
Requires-Dist: toml (>=0.10.2)
Requires-Dist: traitlets (>=5.5.0)
